pysbapi/__init__.py
pysbapi-0.1.1.dist-info/METADATA
pysbapi-0.1.1.dist-info/WHEEL
pysbapi-0.1.1.dist-info/top_level.txt
pysbapi-0.1.1.dist-info/RECORD
